btipay/__init__.py
btipay/btipay.py
btipay/exceptions.py
btipay/responses.py
btipay-0.0.5.dist-info/AUTHORS.rst
btipay-0.0.5.dist-info/LICENSE
btipay-0.0.5.dist-info/METADATA
btipay-0.0.5.dist-info/WHEEL
btipay-0.0.5.dist-info/top_level.txt
btipay-0.0.5.dist-info/RECORD
