Metadata-Version: 2.1
Name: btipay
Version: 0.0.5
Summary: Python package for using the Banca Transilvania iPay API.
Home-page: https://github.com/rolisz/pybtipay
Author: Roland Szabo
Author-email: roland@rolisz.ro
License: MIT
Project-URL: Documentation, https://pybtipay.readthedocs.io/
Project-URL: Changelog, https://pybtipay.readthedocs.io/en/latest/changelog.html
Project-URL: Issue Tracker, https://github.com/rolisz/pybtipay/issues
Platform: UNKNOWN
Classifier: Development Status :: 5 - Production/Stable
Classifier: Intended Audience :: Developers
Classifier: License :: OSI Approved :: MIT License
Classifier: Operating System :: Unix
Classifier: Operating System :: POSIX
Classifier: Operating System :: Microsoft :: Windows
Classifier: Programming Language :: Python
Classifier: Programming Language :: Python :: 3
Classifier: Programming Language :: Python :: 3 :: Only
Classifier: Programming Language :: Python :: 3.6
Classifier: Programming Language :: Python :: 3.7
Classifier: Programming Language :: Python :: 3.8
Classifier: Programming Language :: Python :: 3.9
Classifier: Programming Language :: Python :: Implementation :: CPython
Classifier: Programming Language :: Python :: Implementation :: PyPy
Classifier: Topic :: Utilities
Requires-Python: >=3.6
License-File: LICENSE
License-File: AUTHORS.rst
Requires-Dist: requests (>=2)
Requires-Dist: pydantic (>=1.5)
